README.rst
setup.py
djangocms_restapi/__init__.py
djangocms_restapi/middleware.py
djangocms_restapi/urls.py
djangocms_restapi.egg-info/PKG-INFO
djangocms_restapi.egg-info/SOURCES.txt
djangocms_restapi.egg-info/dependency_links.txt
djangocms_restapi.egg-info/not-zip-safe
djangocms_restapi.egg-info/pbr.json
djangocms_restapi.egg-info/requires.txt
djangocms_restapi.egg-info/top_level.txt