Metadata-Version: 1.1
Name: djangocms-restapi
Version: 0.0.1
Summary: REST api interface for Django CMS
Home-page: https://github.com/inonit/djangocms-restapi
Author: Rolf Håvard Blindheim
Author-email: rolf.blindheim@inonit.no
License: MIT License
Download-URL: https://github.com/inonit/djangocms-restapi.git
Platform: UNKNOWN
Classifier: Operating System :: OS Independent
Classifier: Development Status :: 3 - Alpha
Classifier: Environment :: Web Environment
Classifier: Framework :: Django
Classifier: Intended Audience :: Developers
Classifier: License :: OSI Approved :: MIT License
Classifier: Programming Language :: Python :: 2
Classifier: Programming Language :: Python :: 3
Classifier: Topic :: Software Development :: Libraries :: Python Modules
